pyret/__init__.py
pyret/filtertools.py
pyret/nonlinearities.py
pyret/spiketools.py
pyret/stimulustools.py
pyret/utils.py
pyret/visualizations.py
pyret-0.4.3.dist-info/DESCRIPTION.rst
pyret-0.4.3.dist-info/METADATA
pyret-0.4.3.dist-info/RECORD
pyret-0.4.3.dist-info/WHEEL
pyret-0.4.3.dist-info/metadata.json
pyret-0.4.3.dist-info/top_level.txt
