Metadata-Version: 2.0
Name: pyret
Version: 0.4.3
Summary: Tools for the analysis of neural electrophysiology data
Home-page: https://github.com/baccuslab/pyret
Author: Benjamin Naecker, Niru Maheshwaranathan
Author-email: bnaecker@stanford.edu
License: MIT
Platform: UNKNOWN
Classifier: Intended Audience :: Science/Research
Classifier: Operating System :: MacOS :: MacOS X
Classifier: Topic :: Scientific/Engineering :: Information Analysis
Requires: scipy
Requires: skimage
Requires: numpy
Requires: matplotlib
Requires-Dist: matplotlib
Requires-Dist: numpy
Requires-Dist: scikit-image
Requires-Dist: scipy
